{
  "_fv": 18,
  "_type": "tool",
  "definition": {
    "renderType": 0,
    "texture": "diamonpickaxe",
    "customModelName": "Normal",
    "name": "Diamond Pickacks",
    "specialInfo": [],
    "creativeTab": {
      "value": "CUSTOM:Minecraf"
    },
    "toolType": "Pickaxe",
    "harvestLevel": 1,
    "efficiency": 1.0,
    "attackSpeed": 1.0,
    "enchantability": 0,
    "damageVsEntity": 2.0,
    "usageCount": 30,
    "blocksAffected": [],
    "hasGlow": false,
    "repairItems": [
      {
        "value": "CUSTOM:DiamondIngot"
      }
    ],
    "immuneToFire": false,
    "stayInGridWhenCrafting": false,
    "damageOnCrafting": false
  }
}